site_conn_check/__init__.py
site_conn_check/conn_check.py
site_conn_check/main.py
site_conn_check/sites_db.py
site_conn_check-1.1.0.dist-info/LICENCE
site_conn_check-1.1.0.dist-info/METADATA
site_conn_check-1.1.0.dist-info/WHEEL
site_conn_check-1.1.0.dist-info/entry_points.txt
site_conn_check-1.1.0.dist-info/top_level.txt
site_conn_check-1.1.0.dist-info/RECORD
